{
  "portraitScale": 3.24,
  "portraitTranslation": [-0.71, -2.62, 0],
  "profileScale": 0.77,
  "profileTranslation": [0.0, 0.6, 0],
  "rootBone": "rolycoly",
  "poses": {
    "standing": {
      "poseTypes": ["STAND", "NONE", "PORTRAIT", "PROFILE"],
	  "isBattle": true,
      "animations": [
        "q.bedrock('rolycoly', 'ground_idle')"
      ],
      "quirks": [
        "q.bedrock_quirk('rolycoly', 'blink')"
      ]
    },
    "walking": {
      "poseTypes": ["WALK"],
      "animations": [
        "q.bedrock('rolycoly', 'ground_walk_wip')"
      ],
      "quirks": [
        "q.bedrock_quirk('rolycoly', 'blink')"
      ]
    }
  }
 }